azure/eventgrid/__init__.py
azure/eventgrid/_client.py
azure/eventgrid/_configuration.py
azure/eventgrid/_model_base.py
azure/eventgrid/_patch.py
azure/eventgrid/_serialization.py
azure/eventgrid/_validation.py
azure/eventgrid/_vendor.py
azure/eventgrid/_version.py
azure/eventgrid/py.typed
azure/eventgrid/_legacy/__init__.py
azure/eventgrid/_legacy/_constants.py
azure/eventgrid/_legacy/_event_mappings.py
azure/eventgrid/_legacy/_helpers.py
azure/eventgrid/_legacy/_messaging_shared.py
azure/eventgrid/_legacy/_models.py
azure/eventgrid/_legacy/_policies.py
azure/eventgrid/_legacy/_publisher_client.py
azure/eventgrid/_legacy/_signature_credential_policy.py
azure/eventgrid/_legacy/_version.py
azure/eventgrid/_legacy/_generated/__init__.py
azure/eventgrid/_legacy/_generated/_client.py
azure/eventgrid/_legacy/_generated/_configuration.py
azure/eventgrid/_legacy/_generated/_patch.py
azure/eventgrid/_legacy/_generated/_serialization.py
azure/eventgrid/_legacy/_generated/_vendor.py
azure/eventgrid/_legacy/_generated/py.typed
azure/eventgrid/_legacy/_generated/_operations/__init__.py
azure/eventgrid/_legacy/_generated/_operations/_operations.py
azure/eventgrid/_legacy/_generated/_operations/_patch.py
azure/eventgrid/_legacy/_generated/aio/__init__.py
azure/eventgrid/_legacy/_generated/aio/_client.py
azure/eventgrid/_legacy/_generated/aio/_configuration.py
azure/eventgrid/_legacy/_generated/aio/_patch.py
azure/eventgrid/_legacy/_generated/aio/_vendor.py
azure/eventgrid/_legacy/_generated/aio/_operations/__init__.py
azure/eventgrid/_legacy/_generated/aio/_operations/_operations.py
azure/eventgrid/_legacy/_generated/aio/_operations/_patch.py
azure/eventgrid/_legacy/_generated/models/__init__.py
azure/eventgrid/_legacy/_generated/models/_models.py
azure/eventgrid/_legacy/_generated/models/_patch.py
azure/eventgrid/_legacy/aio/__init__.py
azure/eventgrid/_legacy/aio/_publisher_client_async.py
azure/eventgrid/_operations/__init__.py
azure/eventgrid/_operations/_operations.py
azure_eventgrid-4.21.0.dist-info/LICENSE
azure_eventgrid-4.21.0.dist-info/METADATA
azure_eventgrid-4.21.0.dist-info/WHEEL
azure_eventgrid-4.21.0.dist-info/top_level.txt
azure_eventgrid-4.21.0.dist-info/RECORD
